{
  "version": "1.3.2",
  "name": "twemoji",
  "license": ["MIT", "CC-BY-4.0"],
  "description": "A Unicode standard based way to implement emoji across all platforms.",
  "homepage": "https://github.com/twitter/twemoji",
  "keywords": [
    "emoji",
    "DOM",
    "parser",
    "images",
    "retina",
    "Twitter",
    "unicode"
  ],
  "author": {
    "name": "Twitter, Inc.",
    "web": "https://github.com/twitter/"
  },
  "repository": "twitter/twemoji",
  "main": "twemoji.js",
  "scripts": [
    "twemoji.js"
  ]
}
